pyapep/__init__.py
pyapep/isofit.py
pyapep/simide.py
pyapep/simsep.py
pyapep/simsep_backup.py
pyadserver-0.1.1.dist-info/METADATA
pyadserver-0.1.1.dist-info/WHEEL
pyadserver-0.1.1.dist-info/top_level.txt
pyadserver-0.1.1.dist-info/RECORD
