Metadata-Version: 2.1
Name: pyadserver
Version: 0.1.1
Summary: Python package for Adserver team in KITECH
Home-page: https://github.com/sga2022/
Author: Seongbin Ga
Author-email: sga@kitech.re.kr
License: UNKNOWN
Platform: UNKNOWN
Requires-Python: >=3.6
Requires-Dist: numpy (>=1.20.0)
Requires-Dist: scipy (>=1.5.0)
Requires-Dist: matplotlib (>=3.0.0)
